datos_mex/banxico/__init__.py
datos_mex/banxico/indicadores.py
datos_mex/data_format/__init__.py
datos_mex/data_format/auxiliar.py
datos_mex/inegi/__init__.py
datos_mex/inegi/banco_de_indicadores.py
datos_mex-1.0.4.dist-info/LICENSE.md
datos_mex-1.0.4.dist-info/METADATA
datos_mex-1.0.4.dist-info/WHEEL
datos_mex-1.0.4.dist-info/top_level.txt
datos_mex-1.0.4.dist-info/RECORD
