Metadata-Version: 2.2
Name: datos_mex
Version: 1.0.4
Summary: Consultor del api del Banco de México y del Instituto Nacional de Estadística y Geografía
Home-page: https://github.com/Lu1srojas/datos_mex
Author: Luis Manuel Rojas Patiño
Author-email: luisrojaspatino5@gmail.com
License-File: LICENSE.md
Dynamic: author
Dynamic: author-email
Dynamic: description
Dynamic: description-content-type
Dynamic: home-page
Dynamic: summary
